mondip_ml_tutorials/__init__.py
mondip_ml_tutorials/tutorials.py
mondip_ml_tutorials-0.1.4.dist-info/licenses/LICENSE
mondip_ml_tutorials-0.1.4.dist-info/METADATA
mondip_ml_tutorials-0.1.4.dist-info/WHEEL
mondip_ml_tutorials-0.1.4.dist-info/entry_points.txt
mondip_ml_tutorials-0.1.4.dist-info/top_level.txt
mondip_ml_tutorials-0.1.4.dist-info/RECORD
